pyesapi/Lot.py
pyesapi/__init__.py
pyesapi/stubs/__init__.py
pyesapi/stubs/clr.py
pyesapi/stubs/pythoncom.py
pyesapi/stubs/Microsoft/CSharp.py
pyesapi/stubs/Microsoft/VisualBasic.py
pyesapi/stubs/Microsoft/__init__.py
pyesapi/stubs/Microsoft/Win32/SafeHandles.py
pyesapi/stubs/Microsoft/Win32/__init__.py
pyesapi/stubs/System/Array.py
pyesapi/stubs/System/Configuration.py
pyesapi/stubs/System/Double.py
pyesapi/stubs/System/Int32.py
pyesapi/stubs/System/Media.py
pyesapi/stubs/System/Timers.py
pyesapi/stubs/System/Web.py
pyesapi/stubs/System/__init__.py
pyesapi/stubs/System/Collections/Concurrent.py
pyesapi/stubs/System/Collections/Generic.py
pyesapi/stubs/System/Collections/ObjectModel.py
pyesapi/stubs/System/Collections/Specialized.py
pyesapi/stubs/System/Collections/__init__.py
pyesapi/stubs/System/Runtime/__init__.py
pyesapi/stubs/System/Type/__init__.py
pyesapi/stubs/System/Windows/Input.py
pyesapi/stubs/System/Windows/Markup.py
pyesapi/stubs/System/Windows/__init__.py
pyesapi/stubs/VMS/__init__.py
pyesapi/stubs/VMS/TPS/__init__.py
pyesapi/stubs/VMS/TPS/Common/__init__.py
pyesapi/stubs/VMS/TPS/Common/Model/API.py
pyesapi/stubs/VMS/TPS/Common/Model/Types.py
pyesapi/stubs/VMS/TPS/Common/Model/__init__.py
pyesapi/tools/IdMatcher.py
pyesapi/tools/__init__.py
pyesapi/tools/geometry.py
pyesapi/tools/dose/__init__.py
pyesapi/tools/plans/__init__.py
pyesapi/tools/plans/shape_based_dose.py
pyesapi/tools/structures/__init__.py
pyesapi/tools/structures/dth.py
pyesapi/tools/structures/dvh.py
pyesapi/tools/structures/ovh.py
pyesapi-0.2.5.dist-info/LICENSE
pyesapi-0.2.5.dist-info/METADATA
pyesapi-0.2.5.dist-info/WHEEL
pyesapi-0.2.5.dist-info/top_level.txt
pyesapi-0.2.5.dist-info/RECORD
